{
  "set": "grn",
  "setName": "Guilds of Ravnica",
  "boosterType": "draft",
  "source": "https://mtg.fandom.com/wiki/Guilds_of_Ravnica",
  "notes": "No basic lands in boosters. Boosters included a guildgate in the land slot.",
  "slots": [
    { "name": "rare", "count": 1, "rarities": ["rare", "mythic"], "pool": { "nonfoil": ["1-259"] }, "mythicRate": 0.125 },
    { "name": "uncommon", "count": 3, "rarities": ["uncommon"], "pool": { "nonfoil": ["1-259"] } },
    { "name": "common", "count": 10, "rarities": ["common"], "pool": { "nonfoil": ["1-259"] } }
  ]
}
